setup.py
jdliu_test/__init__.py
jdliu_test/print.py
jdliu_test.egg-info/PKG-INFO
jdliu_test.egg-info/SOURCES.txt
jdliu_test.egg-info/dependency_links.txt
jdliu_test.egg-info/top_level.txt